gg_group_setup/__init__.py
gg_group_setup/cfg.json
gg_group_setup/cmd.py
gg_group_setup/group.py
gg_group_setup/mock_device.py
gg_group_setup/mock_group.py
gg_group_setup-0.5.3.dist-info/METADATA
gg_group_setup-0.5.3.dist-info/RECORD
gg_group_setup-0.5.3.dist-info/WHEEL
gg_group_setup-0.5.3.dist-info/entry_points.txt
gg_group_setup-0.5.3.dist-info/top_level.txt
