Metadata-Version: 2.1
Name: gg-group-setup
Version: 0.5.3
Summary: A file-driven approach to the creation of an entire AWS Greengrass group
Home-page: https://github.com/awslabs/aws-greengrass-group-setup
Author: Brett Francis
Author-email: brettf@amazon.com
License: Apache License 2.0
Keywords: greengrass group aws iot
Platform: UNKNOWN
Classifier: Intended Audience :: Developers
Classifier: Natural Language :: English
Classifier: Environment :: Web Environment
Classifier: License :: OSI Approved :: Apache Software License
Classifier: Operating System :: OS Independent
Classifier: Development Status :: 4 - Beta
Classifier: Programming Language :: Python
Classifier: Programming Language :: Python :: 3.7
Classifier: Topic :: Software Development :: Libraries :: Python Modules
Classifier: Topic :: Utilities
Requires-Dist: boto3 (>=1.7.50)
Requires-Dist: fire (>=0.1.3)
